Metadata-Version: 1.0
Name: marzoog-distributions
Version: 0.1
Summary: Gaussian distributions
Home-page: UNKNOWN
Author: Marzoog AlGhazwi
Author-email: marzoog.tech@gmail.com
License: UNKNOWN
Platform: UNKNOWN
